pg_httpserver/__init__.py
pg_httpserver/define.py
pg_httpserver/fapi.py
pg_httpserver/manager.py
pg_httpserver/models.py
pg_httpserver-1.6.7.dist-info/METADATA
pg_httpserver-1.6.7.dist-info/WHEEL
pg_httpserver-1.6.7.dist-info/top_level.txt
pg_httpserver-1.6.7.dist-info/RECORD
