Metadata-Version: 2.1
Name: pg_httpserver
Version: 1.6.7
Summary: python game: httpserver
Author: baozilaji@gmail.com
Requires-Python: >=3.9
Requires-Dist: pg-ormapping
Requires-Dist: pg-resourceloader
Requires-Dist: aiofiles ==24.1.0
Requires-Dist: fastapi ==0.115.2
Requires-Dist: uvicorn ==0.31.1
